MANIFEST.in
README.rst
setup.py
altf4/__init__.py
altf4/helloworld.py
altf4.egg-info/PKG-INFO
altf4.egg-info/SOURCES.txt
altf4.egg-info/dependency_links.txt
altf4.egg-info/not-zip-safe
altf4.egg-info/requires.txt
altf4.egg-info/top_level.txt