Metadata-Version: 1.1
Name: altf4
Version: 0.0.1
Summary: Automatic Loadtesting Framework 4
Home-page: https://github.com/fabeschan/altf4
Author: Fabian Chan
Author-email: fabeschan@gmail.com
License: MIT
Platform: UNKNOWN
Classifier: Development Status :: 2 - Pre-Alpha
Classifier: License :: OSI Approved :: MIT License
Classifier: Programming Language :: Python :: 2.7
Classifier: Topic :: Software Development :: Testing :: Traffic Generation
